[{"container-title":"Geochemistry, Geophysics, Geosystems","author":[{"given":"Gina M.","family":"Schmalzle"},{"given":"Robert","family":"McCaffrey"},{"given":"Kenneth C.","family":"Creager"}],"DOI":"10.1002/2013gc005172","type":"article-journal","id":"Schmalzle_2014","citation-key":"Schmalzle_2014","ISSN":"1525-2027","issue":"4","issued":{"date-parts":[[2014,4]]},"page":"1515-1532","publisher":"American Geophysical Union (AGU)","title":"Central Cascadia subduction zone creep","URL":"http://dx.doi.org/10.1002/2013GC005172","volume":"15","_graph":[{"type":"@biblatex/text","data":" @article{Schmalzle_2014, title={Central Cascadia subduction zone creep}, volume={15}, ISSN={1525-2027}, url={http://dx.doi.org/10.1002/2013GC005172}, DOI={10.1002/2013gc005172}, number={4}, journal={Geochemistry, Geophysics, Geosystems}, publisher={American Geophysical Union (AGU)}, author={Schmalzle, Gina M. and McCaffrey, Robert and Creager, Kenneth C.}, year={2014}, month=apr, pages={1515–1532} }\n"},{"type":"@biblatex/entries+list"},{"type":"@csl/list+object"}]}]